robust_ai_utils/__init__.py
robust_ai_utils/assert_utils.py
robust_ai_utils/pytest_collector.py
robust_ai_utils/pytest_sandbox.py
robust_ai_utils-0.0.4.dist-info/METADATA
robust_ai_utils-0.0.4.dist-info/WHEEL
robust_ai_utils-0.0.4.dist-info/top_level.txt
robust_ai_utils-0.0.4.dist-info/RECORD
